{
  "pais": {
    "name":"Portugal",
    "color":"#E40521",
    "arqueros": [
      { "nombre": "RUI", "apellido": "PATRICIO", "id": 728 },
      { "nombre": "JOSE", "apellido": "SA", "id": 729 },
      { "nombre": "DIOGO", "apellido": "COSTA", "id": 730 }
    ],
    "defensas": [
      { "nombre": "DIOGO", "apellido": "DALOT", "id": 731 },
      { "apellido": "PEPE", "id": 732 },
      { "nombre": "RUBEN", "apellido": "DIAS", "id": 733 },
      { "nombre": "RAPHAEL", "apellido": "GUERREIRO", "id": 734 },
      { "apellido": "DANILO", "id": 735 },
      { "nombre": "NUNO", "apellido": "MENDES", "id": 736 },
      { "nombre": "JOAO", "apellido": "CANCELO", "id": 737 },
      { "nombre": "ANTONIO", "apellido": "SILVA", "id": 738 }
    ],
    "mediocampistas": [
      { "nombre": "JOAO", "apellido": "PALHINHA", "id": 739 },
      { "nombre": "BRUNO", "apellido": "FERNANDES", "id": 740 },
      { "apellido": "WILLIAM", "id": 741 },
      { "apellido": "VITINHA", "id": 742 },
      { "nombre": "JOAO", "apellido": "MARIO", "id": 743 },
      { "nombre": "RUBEN", "apellido": "NEVES", "id": 744 },
      { "nombre": "MATHEUS", "apellido": "NUNES", "id": 745 },
      { "apellido": "OTAVIO", "id": 746 }
    ],
    "delanteros": [
      { "nombre": "CRISTIANO", "apellido": "RONALDO", "id": 747 },
      { "nombre": "ANDRE", "apellido": "SILVA", "id": 748 },
      { "nombre": "BERNARDO", "apellido": "SILVA", "id": 749 },
      { "nombre": "JOAO", "apellido": "FELIX", "id": 750 },
      { "nombre": "RAFAEL", "apellido": "LEAO", "id": 751 },
      { "nombre": "RICARDO", "apellido": "HORTA", "id": 752 },
      { "nombre": "GONCALO", "apellido": "RAMOS", "id": 753 }
    ]
  }
}
